aida_permissions/__init__.py
aida_permissions/admin.py
aida_permissions/apps.py
aida_permissions/backends.py
aida_permissions/compat.py
aida_permissions/decorators.py
aida_permissions/middleware.py
aida_permissions/permissions.py
aida_permissions/serializers.py
aida_permissions/signals.py
aida_permissions/urls.py
aida_permissions/views.py
aida_permissions/management/commands/audit_permissions.py
aida_permissions/management/commands/init_permissions.py
aida_permissions/migrations/0001_initial.py
aida_permissions/migrations/__init__.py
aida_permissions/models/__init__.py
aida_permissions/models/base.py
aida_permissions/models/permission.py
aida_permissions/models/role.py
aida_permissions/utils/__init__.py
aida_permissions/utils/permissions.py
aida_permissions/utils/user_utils.py
aida_permissions-1.0.2.dist-info/licenses/LICENSE
aida_permissions-1.0.2.dist-info/METADATA
aida_permissions-1.0.2.dist-info/WHEEL
aida_permissions-1.0.2.dist-info/top_level.txt
aida_permissions-1.0.2.dist-info/RECORD
