Metadata-Version: 2.4
Name: aida-permissions
Version: 1.0.2
Summary: A flexible Django roles and permissions extension optimized for DRF and Vue.js
Home-page: https://github.com/hmesfin/aida-permissions
Author: gojjotech
Author-email: gojjotech <admin@gojjotech.com>
License: MIT
Project-URL: Homepage, https://github.com/hmesfin/aida-permissions
Project-URL: Documentation, https://github.com/hmesfin/aida-permissions/blob/main/README.md
Project-URL: Repository, https://github.com/hmesfin/aida-permissions.git
Project-URL: Bug Tracker, https://github.com/hmesfin/aida-permissions/issues
Classifier: Development Status :: 5 - Production/Stable
Classifier: Environment :: Web Environment
Classifier: Framework :: Django
Classifier: Framework :: Django :: 3.2
Classifier: Framework :: Django :: 4.0
Classifier: Framework :: Django :: 4.1
Classifier: Framework :: Django :: 4.2
Classifier: Framework :: Django :: 5.0
Classifier: Framework :: Django :: 5.1
Classifier: Intended Audience :: Developers
Classifier: License :: OSI Approved :: MIT License
Classifier: Operating System :: OS Independent
Classifier: Programming Language :: Python
Classifier: Programming Language :: Python :: 3
Classifier: Programming Language :: Python :: 3.8
Classifier: Programming Language :: Python :: 3.9
Classifier: Programming Language :: Python :: 3.10
Classifier: Programming Language :: Python :: 3.11
Classifier: Programming Language :: Python :: 3.12
Classifier: Topic :: Internet :: WWW/HTTP
Classifier: Topic :: Software Development :: Libraries :: Python Modules
Requires-Python: >=3.8
License-File: LICENSE
Dynamic: author
Dynamic: home-page
Dynamic: license-file
Dynamic: requires-python
